src/__init__.py
src/ez_pydocs.py
ez_pydocs-0.1.1.dist-info/METADATA
ez_pydocs-0.1.1.dist-info/WHEEL
ez_pydocs-0.1.1.dist-info/entry_points.txt
ez_pydocs-0.1.1.dist-info/top_level.txt
ez_pydocs-0.1.1.dist-info/RECORD
