Metadata-Version: 2.1
Name: ez-pydocs
Version: 0.1.1
Summary: Generating python documentation made ez.
Home-page: https://github.com/codingclaw/ez_pydocs
Author: C3NZ
Author-email: cenz@cenz.io
License: MIT
Platform: UNKNOWN
Classifier: License :: OSI Approved :: MIT License
Classifier: Development Status :: 2 - Pre-Alpha
Classifier: Operating System :: POSIX :: Linux
Classifier: Operating System :: MacOS
Requires-Dist: pydoc-markdown (==2.1.3)
